{
  "championId": 711,
  "championName": "Vex",
  "archetypes": [
    {
      "key": "ap",
      "name": "AP Vex",
      "damageType": "AP",
      "note": "Vex AP route for ARAM: Mayhem. Prioritize Witchful Thinking / Eureka as the main augment plan. Strong secondary hits include Big Brain / Jeweled Gauntlet / Juice Box. Build toward Luden's Echo > Sorcerer's Shoes > Shadowflame > Rabadon's Deathcap > Void Staff > Zhonya's Hourglass. Start with Lost Chapter + Health Potion + Health Potion. Cross-checked against metasrc.com and arammayhem.com and dvg.cn.",
      "augments": {
        "core": [
          {
            "id": 97,
            "apiName": "WitchfulThinking",
            "name": "Witchful Thinking"
          },
          {
            "id": 30,
            "apiName": "Eureka",
            "name": "Eureka"
          }
        ],
        "good": [
          {
            "id": 180,
            "apiName": "BigBrain",
            "name": "Big Brain"
          },
          {
            "id": 48,
            "apiName": "JeweledGauntlet",
            "name": "Jeweled Gauntlet"
          },
          {
            "id": 49,
            "apiName": "JuiceBox",
            "name": "Juice Box"
          },
          {
            "id": 11,
            "apiName": "CantTouchThis",
            "name": "Cant Touch This"
          },
          {
            "id": 133,
            "apiName": "MagicMissile",
            "name": "Magic Missile"
          }
        ],
        "trap": []
      },
      "items": [
        {
          "id": 6655,
          "name": "Luden's Echo"
        },
        {
          "id": 3020,
          "name": "Sorcerer's Shoes"
        },
        {
          "id": 4645,
          "name": "Shadowflame"
        },
        {
          "id": 3089,
          "name": "Rabadon's Deathcap"
        },
        {
          "id": 3135,
          "name": "Void Staff"
        },
        {
          "id": 3157,
          "name": "Zhonya's Hourglass"
        }
      ],
      "runes": null,
      "sources": [
        "metasrc.com",
        "arammayhem.com",
        "dvg.cn"
      ],
      "starterItems": [
        {
          "id": 3802,
          "name": "Lost Chapter"
        },
        {
          "id": 2003,
          "name": "Health Potion"
        },
        {
          "id": 2003,
          "name": "Health Potion"
        }
      ],
      "boots": [],
      "optionalItems": []
    }
  ]
}
